{
  "schemaVersion": 1,
  "id": "openboatutils",
  "version": "0.2.2",
  "name": "OpenBoatUtils",
  "description": "Configurable boat physics, from the serverside. Check the wiki (website button) for more information.",
  "authors": [
    "o7Moon"
  ],
  "contact": {
    "repo": "https://github.com/o7Moon/OpenBoatUtils",
    "homepage": "https://github.com/o7Moon/OpenBoatUtils/wiki"
  },
  "license": "MIT",
  "icon": "assets/openboatutils/OpenBoatUtils_small_square.png",
  "environment": "*",
  "entrypoints": {
    "client": [
      "dev.o7moon.openboatutils.client.OpenBoatUtilsClient"
    ],
    "main": [
      "dev.o7moon.openboatutils.OpenBoatUtils"
    ]
  },
  "mixins": [
    "openboatutils.mixins.json"
  ],
  "depends": {
    "fabricloader": ">=${loader_version}",
    "fabric": "*",
    "minecraft": "${minecraft_version}"
  }
}
